crypto_exchange_apis/__init__.py
crypto_exchange_apis/bittrex_tests.py
crypto_exchange_apis/concurrency.py
crypto_exchange_apis/crypto_exchange_apis.py
crypto_exchange_apis/exceptions.py
crypto_exchange_apis/test.py
crypto_exchange_apis/test_manual.py
crypto_exchange_apis/utils.py
crypto_exchange_apis/bitfinex/__init__.py
crypto_exchange_apis/bitstamp/__init__.py
crypto_exchange_apis/bittrex/__init__.py
crypto_exchange_apis/gdax/__init__.py
crypto_exchange_apis/gdax/order_book.py
crypto_exchange_apis/gdax/websocket_client.py
crypto_exchange_apis/itbit/__init__.py
crypto_exchange_apis/poloniex/__init__.py
crypto_exchange_apis/poloniex/concurrency.py
crypto_exchange_apis/poloniex/exceptions.py
crypto_exchange_apis/poloniex/utils.py
crypto_exchange_apis/tuxexchange/__init__.py
crypto_exchange_apis-0.4.0.dist-info/DESCRIPTION.rst
crypto_exchange_apis-0.4.0.dist-info/METADATA
crypto_exchange_apis-0.4.0.dist-info/RECORD
crypto_exchange_apis-0.4.0.dist-info/WHEEL
crypto_exchange_apis-0.4.0.dist-info/metadata.json
crypto_exchange_apis-0.4.0.dist-info/top_level.txt
