Metadata-Version: 2.0
Name: crypto-exchange-apis
Version: 0.4.0
Summary: Cryptocurrenty exchange API wrappers
Home-page: https://github.com/init-industries/crypto-exchange-apis
Author: sneurlax
Author-email: sneurlax@gmail.com
License: MIT
Keywords: cryptocurrency exchange bitcoin trading
Platform: UNKNOWN
Classifier: Development Status :: 3 - Alpha
Classifier: Intended Audience :: Developers
Classifier: Topic :: Software Development :: Build Tools
Classifier: License :: OSI Approved :: MIT License
Classifier: Programming Language :: Python :: 2
Classifier: Programming Language :: Python :: 2.7
Requires-Dist: bintrees
Requires-Dist: websocket
Requires-Dist: websocket-client
